{"ID":2722,"title":"Day 104 &#8211; Rest Day in Sacramento, CA","content":"<p>We had a terrific rest day with Hannah, who took the day off (Daniel sadly had to work). We explored Capitol Park, met up with Mary, another teaching abroad friend of theirs, had a delicious lunch at Sibling, and explored the newly-built Downtown Commons (DoCo) where all three of us got jewelry at Macy&rsquo;s and ate French pastries. Later, back at the ranch we ate Vietnamese food and watched Over the Garden Wall and Ru Paul&rsquo;s Drag Race.  Turns out Sacramento has a lot going for it!<figure><figure><img src=\"https:\/\/bsik-media.nyc3.digitaloceanspaces.com\/wheelie-babes\/12F46389-9943-474E-AD68-95602F66AD3C-768x1024.jpeg\" alt=\"\"><\/figure><figure><img src=\"https:\/\/bsik-media.nyc3.digitaloceanspaces.com\/wheelie-babes\/87664785-D50A-4C4A-8253-EB0A0F281A9E-768x1024.jpeg\" alt=\"\"><\/figure><figure><img src=\"https:\/\/bsik-media.nyc3.digitaloceanspaces.com\/wheelie-babes\/741E1B-D344-4090-8B9F-C5DF55DBCCFF-768x1024.jpeg\" alt=\"\"><\/figure><figure><img src=\"https:\/\/bsik-media.nyc3.digitaloceanspaces.com\/wheelie-babes\/EBE40062-A7F2-4CB0-811A-65F85AF925DD-768x1024.jpeg\" alt=\"\"><\/figure><figure><img src=\"https:\/\/bsik-media.nyc3.digitaloceanspaces.com\/wheelie-babes\/E39C0C5A-0D70-40C6-981F-9DDE4D6E2823-768x1024.jpeg\" alt=\"\"><\/figure><figure><img src=\"https:\/\/bsik-media.nyc3.digitaloceanspaces.com\/wheelie-babes\/47268D8E-368B-4F2F-ADAA-CD723A3AD593-793x1024.jpeg\" alt=\"\"><\/figure><figure><img src=\"https:\/\/bsik-media.nyc3.digitaloceanspaces.com\/wheelie-babes\/C812B34E-9F9E-4297-A37F-904687202700-1024x768.jpeg\" alt=\"\"><\/figure><figure><img src=\"https:\/\/bsik-media.nyc3.digitaloceanspaces.com\/wheelie-babes\/CF8DD4A2-3919-4684-B0B4-96BB8A4989AC-768x1024.jpeg\" alt=\"\"><\/figure><figure><img src=\"https:\/\/bsik-media.nyc3.digitaloceanspaces.com\/wheelie-babes\/8DCEFB95-F79F-4938-BF86-5CB03686D3C2-768x1024.jpeg\" alt=\"\"><\/figure><figure><img src=\"https:\/\/bsik-media.nyc3.digitaloceanspaces.com\/wheelie-babes\/4338B271-B751-4CAE-8C3D-B47118B14C59-768x1024.jpeg\" alt=\"\"><\/figure><figure><img src=\"https:\/\/bsik-media.nyc3.digitaloceanspaces.com\/wheelie-babes\/F0575983-7AAE-4F03-9DB2-C516A7A5B38C-964x1024.jpeg\" alt=\"\"><\/figure><\/figure><\/p>","date":"October 22, 2022","fields":{"date":"10\/20\/2022","day_number":"104","multiple_days":false,"weather":"Sunny","locations":{"single":true,"start":"Sacramento, CA","end":""},"miles_and_elevation":{"rest_day":true,"miles":"","elevation_gain":"","elevation_loss":"","flats":""}}}